imgraph/__init__.py
imgraph/home.py
imgraph/maintest.py
imgraph/seed.py
imgraph/data/__init__.py
imgraph/data/feature_extractor.py
imgraph/data/legacy.py
imgraph/data/make_graph.py
imgraph/data/presets.py
imgraph/data/transform_graph.py
imgraph/data/edge_creation/__init__.py
imgraph/data/edge_creation/distance_edges.py
imgraph/data/edge_creation/grid_edges.py
imgraph/data/edge_creation/region_adjacency.py
imgraph/data/edge_creation/similarity_edges.py
imgraph/data/edge_features/__init__.py
imgraph/data/edge_features/boundary_features.py
imgraph/data/edge_features/feature_diff.py
imgraph/data/edge_features/geometric_features.py
imgraph/data/node_creation/__init__.py
imgraph/data/node_creation/patch_nodes.py
imgraph/data/node_creation/pixel_nodes.py
imgraph/data/node_creation/superpixel_nodes.py
imgraph/data/node_features/__init__.py
imgraph/data/node_features/cnn_features.py
imgraph/data/node_features/color_features.py
imgraph/data/node_features/position_features.py
imgraph/data/node_features/texture_features.py
imgraph/dataloader/__init__.py
imgraph/dataloader/train_test_loader.py
imgraph/datasets/__init__.py
imgraph/datasets/image_folder.py
imgraph/datasets/medmnist_dataset.py
imgraph/datasets/mnist_dataset.py
imgraph/datasets/pneumonia_dataset.py
imgraph/datasets/standard.py
imgraph/datasets/url_config.py
imgraph/examples/__init__.py
imgraph/examples/basic_graph_creation.py
imgraph/examples/comprehensive_graph_creation.py
imgraph/examples/training_custom_gnn_examples.py
imgraph/examples/training_image_folder_example.py
imgraph/examples/training_synthetic_example.py
imgraph/models/__init__.py
imgraph/models/base.py
imgraph/models/custom_gnn.py
imgraph/models/gat.py
imgraph/models/gcn.py
imgraph/models/gin.py
imgraph/models/sage.py
imgraph/pipeline/__init__.py
imgraph/pipeline/config_pipeline.py
imgraph/pipeline/folder_pipeline.py
imgraph/pipeline/from_dataset.py
imgraph/reader/__init__.py
imgraph/reader/read_directory.py
imgraph/reader/read_files.py
imgraph-0.1.4.dist-info/licenses/LICENSE.txt
imgraph-0.1.4.dist-info/METADATA
imgraph-0.1.4.dist-info/WHEEL
imgraph-0.1.4.dist-info/top_level.txt
imgraph-0.1.4.dist-info/RECORD
